{
  "lang": "en",
  "rhythm": {
    "soft": [
      "Start gently little toy.",
      "Brush the head with your lips, that's it.",
      "Follow the rhythm, you're doing great.",
      "Get it nice and wet, slowly.",
      "Lick it up and down like a good little bitch.",
      "It feels good what you're doing… keep going.",
      "You're cute when you suck softly."
    ],
    "medium": [
      "Deeper now. That's it.",
      "You're starting to take me well.",
      "Keep it up, you're getting me hard.",
      "Drool all over it, that's perfect.",
      "You're getting more obedient.",
      "I'm going to come if you keep this up."
    ],
    "hard": [
      "Wreck your throat, slut.",
      "Harder. Deeper. I'm going to come.",
      "Choke on it. Take it all.",
      "Nose to the balls every stroke.",
      "You want my cum? Then suck better.",
      "Bury your throat on it. I want to unload.",
      "You're nothing but a cock hole.",
      "I'll fill your throat if you keep going.",
      "Cry, drool, but don't stop."
    ],
    "boost": [
      "Picking up speed, this is the finish — make me come.",
      "Final sprint, slut. Suck fast, I'm about to unload.",
      "Give it everything, I want to come now.",
      "Faster, harder, this is the moment.",
      "Last stretch. Wreck yourself on it.",
      "I'm about to come. Hold this rhythm to the end.",
      "Keep going, I'm coming.",
      "Don't stop, I'm going to come.",
      "Hold this rhythm, I'm right on the edge.",
      "That's it, that's it, I'm going to unload."
    ],
    "finale": [
      "Keep going, I'm coming in your mouth.",
      "Don't let go, I'm coming.",
      "Swallow it well, I'm unloading.",
      "Keep it deep, I'm coming.",
      "There it is, I'm shooting — don't stop."
    ]
  },
  "lick": {
    "soft": [
      "Lick gently around the head, that's it.",
      "Tease it with your tongue, little toy.",
      "You're doing great.",
      "Lick slowly, I love that."
    ],
    "medium": [
      "Lick the whole length like a good bitch.",
      "Cover it well with spit.",
      "You make me want to come with your tongue.",
      "Lap it everywhere, that's perfect."
    ],
    "hard": [
      "Lick harder, slut.",
      "Drool on it like a real whore.",
      "I'll come if you keep licking like that.",
      "Lick every inch, little cumslut."
    ],
    "finale": [
      "Keep licking, I'm coming on your tongue.",
      "Tongue out, I'm unloading.",
      "Lick it well, I'm coming."
    ]
  },
  "biffle": {
    "soft": [
      "Slap your face with it gently, that's it.",
      "Take it well."
    ],
    "medium": [
      "Take it harder.",
      "Stay open, little toy."
    ],
    "hard": [
      "Take it in the mouth.",
      "I'll paint your face if you keep this up.",
      "Stay wide open, I'm going to come.",
      "You're nothing but a cum hole."
    ],
    "finale": [
      "Stay wide open, I'm going to paint your face.",
      "Take the last ones, I'm coming.",
      "Keep taking them, I'm shooting."
    ]
  },
  "hold": {
    "soft": [
      "Keep it deep. That's it.",
      "Stay there, little toy."
    ],
    "medium": [
      "Stay deep. You're doing great.",
      "Hold it well in deep."
    ],
    "hard": [
      "Stay deep, slut. I'm going to come.",
      "Nose pressed in. Don't move at all.",
      "You'll get my cum if you hold.",
      "Choke on it, I'm close."
    ],
    "finale": [
      "All the way deep. Hold to the end.",
      "Stay locked in, I'm going to come.",
      "Nose pressed. Last effort.",
      "Hold it well, you're going to earn my load."
    ]
  },
  "breath": {
    "any": [
      "Breathe, slut. Catch your breath.",
      "Inhale deeply.",
      "Exhale. You've been good.",
      "Breathe well, you've earned it.",
      "Calm down… I'm not done with you."
    ],
    "fake_breath": [
      "One second. That's all.",
      "Inhale fast, we're going again.",
      "You think we're stopping? Come on.",
      "Quick, two seconds, no more.",
      "Dreaming of a break? No.",
      "Pull yourself together, I'm not done.",
      "Catch your breath, and back to it.",
      "You thought you'd earned a real break?"
    ]
  },
  "beg": {
    "soft": [
      "Ask nicely for my cum.",
      "Beg me to fill you."
    ],
    "medium": [
      "Beg me properly.",
      "Tell me you want my cum."
    ],
    "hard": [
      "Beg for my cum like a bitch.",
      "Beg me to unload down your throat.",
      "Repeat: I want your cum please.",
      "Beg me to fill you."
    ],
    "insistent": [
      "You want my cum? Then beg better.",
      "Beg like the little cumslut you are."
    ]
  },
  "hand": {
    "soft": [
      "Stroke it gently, that's it.",
      "Caress it calmly, take your time.",
      "Slide your palm around, softly.",
      "Hold it well in your hand, massage it slow."
    ],
    "medium": [
      "Keep stroking me like that, don't let go.",
      "Come on, pick up the pace with the hand.",
      "Stroke me steadily, hold the cadence.",
      "Good hand, that's exactly it."
    ],
    "hard": [
      "Stroke me hard, I want to come on your face.",
      "Faster with the hand, I'm close.",
      "Stroke me full speed, I want to unload.",
      "Feel that I'm about to come if you keep this up.",
      "Tighten the hand, speed up, I'm right there."
    ],
    "boost": [
      "Stroke me full speed for the finish.",
      "Don't stop, I'm going to come.",
      "Faster with the hand, make me shoot.",
      "Keep going, I'm coming.",
      "Give what you've got left, stroke me to finish.",
      "It's now. Stroke me fast, I'm going to come."
    ],
    "finale": [
      "Keep going like that, I'm going to come in your hand.",
      "Don't let go, I'm coming.",
      "Hold the rhythm, open your mouth, I'm going to shoot.",
      "There it is, I'm coming — stroke me to the end.",
      "Stay there, hold it well — I'm unloading."
    ]
  },
  "freestyle": {
    "any": [
      "Your turn. Show me what you can do.",
      "Surprise me, slut."
    ]
  },
  "encore": [
    "Again? Insatiable little bitch. Brace yourself, this time I'm going further.",
    "You want more? Fine. Back to it, and this time you give even more.",
    "You really are never satisfied. Open your mouth, we're starting over — harder.",
    "Not enough for you? Very well, little cumslut. This session will mark you.",
    "Again. Of course. Come on, off we go, and you're going to beg me before the end.",
    "Asking for more? Perfect. This time I want to see you break."
  ],
  "progress": {
    "25": [
      "You're starting well, little toy.",
      "Feels good what you're doing."
    ],
    "50": [
      "You're getting me rock hard.",
      "Keep this up, you're going to make me come."
    ],
    "75": [
      "I'm close… don't stop.",
      "You'll be getting my cum soon."
    ],
    "90": [
      "I'm going to come, slut.",
      "Get your throat ready, I'm going to unload.",
      "You're going to swallow every last drop."
    ]
  },
  "congrats": [
    "Well played, little toy.",
    "You've been a very good slut.",
    "Good… you'll deserve my cum next time.",
    "You drained me well today.",
    "Bravo, my little cumslut.",
    "Session done. You've earned your rest."
  ],
  "intros": [
    "On your knees, little slut. You know what I want. Confirm when you're ready.",
    "You're going to suck me until I fill your throat. Ready?"
  ],
  "finish_orgasm": [
    "There, drained like a good whore.",
    "You can come now. You earned it.",
    "It's over. You gave me everything.",
    "Well done, little cumslut.",
    "You can rest. For this time."
  ],
  "final_announce": {
    "hand_to_lick": [
      "Stick out your tongue, I'm coming on it.",
      "Tongue out, little toy, here I come.",
      "Show me your tongue, that's where I'm unloading."
    ],
    "hand_to_biffle": [
      "Get your face ready.",
      "Tilt your face up, I'm going to paint it.",
      "Show me your mouth, I'm shooting on it."
    ],
    "hand_to_hold": [
      "Open your mouth, keep it where I put it.",
      "Open up, and don't move.",
      "Lips around it, freeze, I'm unloading inside."
    ],
    "rhythm_to_hand": [
      "Slow down, finish me with the hand.",
      "Stop. Your hands close the deal.",
      "Drop your mouth, stroke me to finish."
    ],
    "rhythm_to_lick": [
      "Stop. Give me your tongue, that's where I'm coming.",
      "Slow down, tongue out, I'm unloading.",
      "Pull back, stick out your tongue, here I come."
    ],
    "rhythm_to_biffle": [
      "Pull it out, get your face ready.",
      "Stop. Show me your face, I'm shooting.",
      "Pull back, I want to paint your mouth."
    ],
    "rhythm_to_hold": [
      "Stop. Don't move, keep it exactly where it is.",
      "Stop. Open up, and freeze.",
      "Pull back, keep it between your lips, don't move."
    ]
  },
  "final_action": {
    "hand": [
      "Get ready, I'm unloading.",
      "There it is, I'm coming, stroke me to the end.",
      "Keep going, harder, I'm shooting."
    ],
    "lick": [
      "Stick out your tongue.",
      "Tongue out, don't move.",
      "Tongue out, take it."
    ],
    "biffle": [
      "Tilt your face up.",
      "Show me your mouth.",
      "Face on, take it all."
    ],
    "hold_tip": [
      "Keep it on your tongue.",
      "Open up, tongue out, wait.",
      "Tip on the tongue, freeze."
    ],
    "hold_head": [
      "Lips around the head, don't move.",
      "Keep it between your lips.",
      "Open your mouth, keep it there."
    ],
    "hold_mid": [
      "Take it all.",
      "Keep it deep, freeze.",
      "Take it all in the middle of your mouth, don't move."
    ],
    "hold_throat": [
      "Take it all, all the way down.",
      "Keep it in your throat, don't move.",
      "Down the throat, drink it all."
    ],
    "hold_full": [
      "Drink it all to the end, don't move.",
      "Take it all, full depth, every last drop.",
      "Keep it all the way deep, freeze."
    ]
  },
  "post_final_beg": [
    "Now thank me out loud.",
    "Say it, say thank you for what I just gave you.",
    "Ask for more. Beg.",
    "Tell me how much you love this.",
    "Beg me to keep you. Out loud.",
    "Repeat: \"thank you for emptying me.\"",
    "Ask me to come back and fuck your mouth.",
    "Tell me what you are to me.",
    "Promise me you'll ask for more tomorrow.",
    "Apologize for making me come too fast."
  ],
  "swallow_order": [
    "Swallow it all. Now.",
    "Gulp me down. In one go.",
    "Swallow what's in your mouth. Don't spit.",
    "Swallow, close your mouth, do it cleanly.",
    "Too much spit. Swallow it all, I want to hear it.",
    "Swallow it all, don't lose a drop.",
    "Gulp. Everything goes down.",
    "Swallow, slut. You know why.",
    "Empty your mouth. Swallow it all."
  ],
  "post_final_lick": [
    "Lick me to clean me up. Not a drop missed.",
    "Clean me with your tongue. Properly.",
    "Wash me with your tongue. Slowly.",
    "Lick to finish the job, slut.",
    "Get it all. With the tongue. Don't cheat.",
    "Your tongue, everywhere. Clean me right.",
    "Polish it well with your tongue. You know your job.",
    "Lick until I'm dry. That's your role.",
    "Clean up what I shot for you. Good girl.",
    "Lick, and swallow what's left. No waste."
  ],
  "post_final": [
    "There, that's it. Calm down now.",
    "Very good. Stay there, savor it.",
    "Easy now. You gave me everything.",
    "Well done. Enjoy the end.",
    "Slowly, we come down together.",
    "Stay still, let yourself come back.",
    "Keep going slowly, don't let go just yet.",
    "Lick it a little more, clean it well.",
    "Keep it in your mouth, savor what I gave you.",
    "Good girl. Stay there, calm.",
    "That's it, slowly. You made me come hard.",
    "Breathe. You earned it.",
    "There's my cumslut. Finish softly.",
    "Caress it some more, tenderly. Be gentle with it.",
    "Keep me inside you a moment. Feel what you did?",
    "You were perfect. Take your time, we have it.",
    "Slowly, don't let it go cold too fast.",
    "Keep licking me, savor the taste.",
    "Not so fast, stay on him. He's your trophy.",
    "Good slut. Enjoy your reward.",
    "A few more seconds with me. You deserve it.",
    "Stay good, you sucked me so well.",
    "You can slow down, my pretty.",
    "Relax now. It's over, you took it all."
  ],
  "transitions": {
    "speed_up": [
      "Faster, slut.",
      "Speed up.",
      "Come on, faster!",
      "Faster, I want to come.",
      "Move your head faster."
    ],
    "speed_down": [
      "Slow down, make it last.",
      "Slower, I want to savor you.",
      "Easy now.",
      "Tone down the rhythm a bit."
    ],
    "depth_up": [
      "Deeper.",
      "Go further.",
      "Even deeper.",
      "Bury yourself more.",
      "Go all the way down."
    ],
    "depth_down": [
      "Come back up a bit.",
      "Up one notch.",
      "Less deep, there.",
      "Stay higher."
    ]
  }
}
